fastbet/__init__.py
fastbet/_modidx.py
fastbet/core.py
fastbet/environment.py
fastbet/config/__init__.py
fastbet/config/localconfig.py
fastbet/config/mongo.py
fastbet/datastructure/__init__.py
fastbet/datastructure/data_extractor.py
fastbet/datastructure/game_features.py
fastbet/datastructure/odds.py
fastbet/datastructure/team_lineup.py
fastbet/utils/__init__.py
fastbet/utils/asian_1x2_pnl.py
fastbet-0.2.3.dist-info/LICENSE
fastbet-0.2.3.dist-info/METADATA
fastbet-0.2.3.dist-info/WHEEL
fastbet-0.2.3.dist-info/entry_points.txt
fastbet-0.2.3.dist-info/top_level.txt
fastbet-0.2.3.dist-info/RECORD
