Metadata-Version: 2.1
Name: fastbet
Version: 0.2.3
Summary: Create a custom gym environment to simulate simple betting strategy.
Home-page: https://github.com/real-analytics-rd/fastbet
Author: Tarak Kharrat and Meher Kharbachi
Author-email: tarak@realanalytics.co.uk
License: Apache Software License 2.0
Keywords: notebook python gym reinforcement-learning football
Classifier: Development Status :: 4 - Beta
Classifier: Intended Audience :: Developers
Classifier: Natural Language :: English
Classifier: Programming Language :: Python :: 3.9
Classifier: Programming Language :: Python :: 3.10
Classifier: License :: OSI Approved :: Apache Software License
Requires-Python: >=3.9
License-File: LICENSE
Requires-Dist: fastcore (>=1.5.8)
Requires-Dist: pandas (>=1.5.3)
Requires-Dist: numpy (>=1.23)
Requires-Dist: toml (>=0.10)
Requires-Dist: mongoengine (>=0.26)
Requires-Dist: gym (>=0.26)
Requires-Dist: plotly (>=5.13.0)
Requires-Dist: requests (>=2.28.2)
Requires-Dist: ipykernel (>=6.21.2)
Requires-Dist: nbformat (>=5.7.3)
Requires-Dist: tqdm (>=4.65)
Requires-Dist: kaleido (>=0.2.1)
Provides-Extra: dev
Requires-Dist: nbdev (>=2.3.12) ; extra == 'dev'
